kataCheckout/__init__.py
kataCheckout/kataCheckout.py
kataCheckout-2.0.2.dist-info/LICENSE
kataCheckout-2.0.2.dist-info/METADATA
kataCheckout-2.0.2.dist-info/WHEEL
kataCheckout-2.0.2.dist-info/top_level.txt
kataCheckout-2.0.2.dist-info/RECORD
