Metadata-Version: 2.1
Name: kataCheckout
Version: 2.0.2
Summary: Python package for kataCheckout
Author: Alejandro Beltre
Author-email: alejandro.beltre134@gmail.com
Keywords: python,first package
Classifier: Development Status :: 3 - Alpha
Classifier: Intended Audience :: Education
Classifier: Programming Language :: Python :: 2
Classifier: Programming Language :: Python :: 3
Classifier: Operating System :: MacOS :: MacOS X
Classifier: Operating System :: Microsoft :: Windows
License-File: LICENSE
